booth_multiplier.v
module booth_multiplier #(parameter N = 4)(
    input clk,
    input rst,
    input start,
    input signed [N-1:0] multiplicand,
    input signed [N-1:0] multiplier,
    output reg signed [(2*N)-1:0] product,
    output reg done
);

    reg signed [N:0] A, S;
    reg signed [2*N:0] P;
    reg [N:0] count;

    always @(posedge clk or posedge rst) begin
        if (rst) begin
            A <= 0;
            S <= 0;
            P <= 0;
            product <= 0;
            done <= 0;
            count <= 0;
        end else if (start) begin
            A <= {multiplicand, N+1'b0};       
            S <= {-multiplicand, N+1'b0};      
            P <= { {N{1'b0}}, multiplier, 1'b0 }; 
            count <= N;
            done <= 0;
        end else if (count > 0) begin
            case (P[1:0])
                2'b01: P[2*N:N] <= P[2*N:N] + A;
                2'b10: P[2*N:N] <= P[2*N:N] + S;
            endcase
            P <= $signed(P) >>> 1;
            count <= count - 1;

            if (count == 1) begin
                product <= P[2*N-1:0];
                done <= 1;
            end
        end
    end
endmodule

booth_multiplier_tb.v
module booth_tb;

    reg clk = 0;
    reg rst;
    reg start;
    reg signed [3:0] multiplicand;
    reg signed [3:0] multiplier;
    wire signed [7:0] product;
    wire done;

    booth_multiplier #(4) uut (
        .clk(clk),
        .rst(rst),
        .start(start),
        .multiplicand(multiplicand),
        .multiplier(multiplier),
        .product(product),
        .done(done)
    );

       always #5 clk = ~clk;

    initial begin
                $dumpfile("booth.vcd");
        $dumpvars(0, booth_tb);
        $display("Time\tStart\tMplicand\tMultiplier\tProduct\t\tDone");
        $display("-------------------------------------------------------------");

        rst = 1; start = 0;
        multiplicand = 0; multiplier = 0;
        #10;

        rst = 0;

        // Test Case 1: -3 x 5 = -15
        multiplicand = -3;
        multiplier = 5;
        start = 1;
        #10 start = 0;

        wait(done);
        $display("%4t\t%b\t%d\t\t%d\t\t%d\t%b", $time, start, multiplicand, multiplier, product, done);

        // Test Case 2: -4 x -2 = 8
        #10;
        multiplicand = -4;
        multiplier = -2;
        start = 1;
        #10 start = 0;

        wait(done);
        $display("%4t\t%b\t%d\t\t%d\t\t%d\t%b", $time, start, multiplicand, multiplier, product, done);

        // Test Case 3: 7 x 3 = 21
        #10;
        multiplicand = 7;
        multiplier = 3;
        start = 1;
        #10 start = 0;

        wait(done);
        $display("%4t\t%b\t%d\t\t%d\t\t%d\t%b", $time, start, multiplicand, multiplier, product, done);

        $finish;
    end
endmodule

booth.vcd
$date
	Sat Jul 26 15:35:44 2025
$end
$version
	Icarus Verilog
$end
$timescale
	1s
$end
$scope module booth_tb $end
$var wire 8 ! product [7:0] $end
$var wire 1 " done $end
$var reg 1 # clk $end
$var reg 4 $ multiplicand [3:0] $end
$var reg 4 % multiplier [3:0] $end
$var reg 1 & rst $end
$var reg 1 ' start $end
$scope module uut $end
$var wire 1 # clk $end
$var wire 4 ( multiplicand [3:0] $end
$var wire 4 ) multiplier [3:0] $end
$var wire 1 & rst $end
$var wire 1 ' start $end
$var parameter 32 * N $end
$var reg 5 + A [4:0] $end
$var reg 9 , P [8:0] $end
$var reg 5 - S [4:0] $end
$var reg 5 . count [4:0] $end
$var reg 1 " done $end
$var reg 8 / product [7:0] $end
$upscope $end
$upscope $end
$enddefinitions $end
$comment Show the parameter values. $end
$dumpall
b100 *
$end
#0
$dumpvars
b0 /
b0 .
b0 -
b0 ,
b0 +
b0 )
b0 (
0'
1&
b0 %
b0 $
0#
0"
b0 !
$end
#5
1#
#10
0#
1'
b101 %
b101 )
b1101 $
b1101 (
0&
#15
b100 .
b1010 ,
b100 -
b100 +
1#
#20
0#
0'
#25
b11 .
b101 ,
1#
#30
0#
#35
b10 .
b10 ,
1#
#40
0#
#45
b1 .
b1 ,
1#
#50
0#
#55
1"
b1 !
b1 /
b0 .
b0 ,
1#
#60
0#
#65
0"
b100 .
b11100 ,
1#
1'
b1110 %
b1110 )
b1100 $
b1100 (
#70
0#
#75
b11 .
b1110 ,
1#
0'
#80
0#
#85
b10 .
b111 ,
1#
#90
0#
#95
b1 .
b11 ,
1#
#100
0#
#105
1"
b11 !
b11 /
b0 .
b1 ,
1#
#110
0#
#115
0"
b100 .
b110 ,
1#
1'
b11 %
b11 )
b111 $
b111 (
#120
0#
#125
b11 .
b11 ,
1#
0'
#130
0#
#135
b10 .
b1 ,
1#
#140
0#
#145
b1 .
b0 ,
1#
#150
0#
#155
1"
b0 !
b0 /
b0 .
1#
